fith/__init__.py
fith/asm5.py
fith/baselib.fth
fith/fith.py
fith/vm5.py
fithlang-0.2.1.dist-info/LICENSE
fithlang-0.2.1.dist-info/METADATA
fithlang-0.2.1.dist-info/WHEEL
fithlang-0.2.1.dist-info/entry_points.txt
fithlang-0.2.1.dist-info/top_level.txt
fithlang-0.2.1.dist-info/RECORD
