Metadata-Version: 2.1
Name: fithlang
Version: 0.2.1
Summary: The Fith programming language and 5vm compiler and tools
Home-page: https://github.com/mishaklopukh/fithlang/
Author: Misha Klopukh
Author-email: mklopukh2019@fau.edu
License: MIT
Project-URL: Documentation, https://mishaklopukh.github.io/fithlang/
Platform: UNKNOWN
Classifier: Development Status :: 3 - Alpha
Classifier: License :: OSI Approved :: MIT License
Classifier: Programming Language :: Python :: 3.8
Classifier: Operating System :: OS Independent
Classifier: Topic :: Software Development :: Compilers
License-File: LICENSE
